pyspark_gcs/__init__.py
pyspark_gcs/py.typed
pyspark_gcs/spark_utils.py
pyspark_gcs/jars/gcs-connector-hadoop3-2.2.6-shaded.jar
pyspark_gcs/tests/__init__.py
pyspark_gcs/tests/spark_utils_test.py
pyspark_gcs-2.2.6.1.dist-info/LICENSE
pyspark_gcs-2.2.6.1.dist-info/METADATA
pyspark_gcs-2.2.6.1.dist-info/WHEEL
pyspark_gcs-2.2.6.1.dist-info/top_level.txt
pyspark_gcs-2.2.6.1.dist-info/RECORD
