Metadata-Version: 2.1
Name: pyspark-gcs
Version: 2.2.6.1
Summary: pyspark with GCS batteries
Home-page: https://github.com/ravwojdyla/pyspark_gcs
Author: Rafal Wojdyla
License: Apache
Platform: UNKNOWN
Classifier: Development Status :: 2 - Pre-Alpha
Classifier: License :: OSI Approved :: Apache Software License
Classifier: Operating System :: OS Independent
Classifier: Programming Language :: Python
Classifier: Programming Language :: Python :: 3
Requires-Python: >=3.7
License-File: LICENSE
Requires-Dist: pyspark
